twinlab/__init__.py
twinlab/_api/__init__.py
twinlab/_api/_utils.py
twinlab/_api/core.py
twinlab/_api/datasets.py
twinlab/_api/designs.py
twinlab/_api/emulators.py
twinlab/_api/projects.py
twinlab/_beta/params.py
twinlab/_plotting.py
twinlab/_utils.py
twinlab/_version.py
twinlab/core.py
twinlab/dataset.py
twinlab/distributions.py
twinlab/emulator.py
twinlab/helper.py
twinlab/params.py
twinlab/prior.py
twinlab/project.py
twinlab/sampling.py
twinlab/settings.py
twinlab-2.21.0.dist-info/METADATA
twinlab-2.21.0.dist-info/WHEEL
twinlab-2.21.0.dist-info/RECORD
