Metadata-Version: 2.3
Name: twinlab
Version: 2.21.0
Summary: twinLab - Probabilistic Machine Learning for Engineers
Keywords: machine-learning,AI,cloud,twinLab,digiLab
Author: digiLab Solutions Ltd.
Author-email: twinlab@digilab.co.uk
Maintainer: twinLab Product Team
Maintainer-email: twinlab@digilab.co.uk
Requires-Python: >=3.9,<3.13
Classifier: Programming Language :: Python :: 3
Classifier: Programming Language :: Python :: 3.9
Classifier: Programming Language :: Python :: 3.10
Classifier: Programming Language :: Python :: 3.11
Classifier: Programming Language :: Python :: 3.12
Requires-Dist: deprecated (>=1.2.14,<2.0.0)
Requires-Dist: kiwisolver (==1.4.6)
Requires-Dist: matplotlib (>=3.7,<4.0)
Requires-Dist: numpy (>=1.26,<2.0)
Requires-Dist: pandas (>=2.1.4,<3.0.0)
Requires-Dist: python-dotenv (>=1.0.0,<2.0.0)
Requires-Dist: requests (>=2.28.2,<3.0.0)
Requires-Dist: typeguard (>=4.0.0,<5.0.0)
Project-URL: Documentation, https://twinlab.ai
Project-URL: Homepage, https://twinlab.ai
